agent_mont/__init__.py
agent_mont/cost_calculator.py
agent_mont/logger.py
agent_mont/monitor.py
agent_mont/old_monitor.py
agent_mont/utils.py
agent_mont/visualizer.py
agent_mont-0.1.3.dist-info/licenses/LICENSE
tests/__init__.py
tests/test_agent_mont.py
agent_mont-0.1.3.dist-info/METADATA
agent_mont-0.1.3.dist-info/WHEEL
agent_mont-0.1.3.dist-info/top_level.txt
agent_mont-0.1.3.dist-info/RECORD
