Metadata-Version: 2.4
Name: agent-mont
Version: 0.1.3
Summary: A comprehensive monitoring solution for AI agent frameworks including Langchain, CrewAI, and Agno. AgentMont provides enhanced metrics and deep observability for production AI agent applications.
Home-page: https://github.com/ansarifaisal12/Agent_Monts.git
Author: Faisal (BizTech)
Author-email: faisalazeeii786@gmail.com
Classifier: Programming Language :: Python :: 3
Classifier: License :: OSI Approved :: MIT License
Classifier: Operating System :: OS Independent
Requires-Python: >=3.8
License-File: LICENSE
Requires-Dist: psutil
Requires-Dist: matplotlib
Requires-Dist: streamlit
Requires-Dist: tiktoken
Dynamic: author
Dynamic: author-email
Dynamic: classifier
Dynamic: description
Dynamic: description-content-type
Dynamic: home-page
Dynamic: license-file
Dynamic: requires-dist
Dynamic: requires-python
Dynamic: summary
